mycalc/calculator.py
htam26122001-0.0.1.dist-info/METADATA
htam26122001-0.0.1.dist-info/WHEEL
htam26122001-0.0.1.dist-info/top_level.txt
htam26122001-0.0.1.dist-info/RECORD
