Metadata-Version: 2.1
Name: htam26122001
Version: 0.0.1
Summary: my calculator
Home-page: https://github.com/htam2612/calc0001
Download-URL: https://github.com/htam2612/calc0001/archive/refs/tags/v0.0.1.zip
Author: huutam
License: UNKNOWN
Platform: UNKNOWN
Classifier: Programming Language :: Python :: 3
